plenary/__init__.py
plenary/chain.py
plenary/classes.py
plenary/constant.py
plenary/exception.py
plenary/generate.py
plenary/git.py
plenary/hints.py
plenary/iterate.py
plenary/localtime.py
plenary/metadata.py
plenary/path.py
plenary/proxy.py
plenary/py.typed
plenary/storage.py
plenary/string.py
plenary/wake.py
plenary-1.6.4.dist-info/LICENSE.txt
plenary-1.6.4.dist-info/WHEEL
plenary-1.6.4.dist-info/METADATA
plenary-1.6.4.dist-info/RECORD
