Metadata-Version: 2.1
Name: plenary
Version: 1.6.4
Summary: A library of convenient utility methods and classes
Home-page: https://github.com/swinburne-sensing/plenary
License: GPL-3.0-only
Author: Chris Harrison
Author-email: 629204+ravngr@users.noreply.github.com
Requires-Python: >=3.7,<4.0
Classifier: License :: OSI Approved :: GNU General Public License v3 (GPLv3)
Classifier: Programming Language :: Python :: 3
Classifier: Programming Language :: Python :: 3.7
Classifier: Programming Language :: Python :: 3.8
Classifier: Programming Language :: Python :: 3.9
Classifier: Programming Language :: Python :: 3.10
Classifier: Programming Language :: Python :: 3.11
Project-URL: Repository, https://github.com/swinburne-sensing/plenary
